rd6006/__init__.py
rd6006/rd6006.py
rd6006-0.2.dist-info/LICENSE
rd6006-0.2.dist-info/METADATA
rd6006-0.2.dist-info/WHEEL
rd6006-0.2.dist-info/top_level.txt
rd6006-0.2.dist-info/RECORD
