Metadata-Version: 2.1
Name: rd6006
Version: 0.2
Summary: Python bindings for RD6006
Author-email: Baldanos <balda@balda.ch>
License: Apache License
Project-URL: Repository, https://github.com/Baldanos/rd6006
License-File: LICENSE
Requires-Dist: pyserial
Requires-Dist: minimalmodbus
